meppel_afvalkalender/__init__.py
meppel_afvalkalender/__version__.py
meppel_afvalkalender/const.py
meppel_afvalkalender/exceptions.py
meppel_afvalkalender/meppel_afvalkalender.py
meppel_afvalkalender-0.3.2.dist-info/LICENSE.md
meppel_afvalkalender-0.3.2.dist-info/METADATA
meppel_afvalkalender-0.3.2.dist-info/WHEEL
meppel_afvalkalender-0.3.2.dist-info/top_level.txt
meppel_afvalkalender-0.3.2.dist-info/RECORD
