Metadata-Version: 2.1
Name: meppel-afvalkalender
Version: 0.3.2
Summary: Asynchronous Python client for Meppel Afvalkalender API.
Home-page: https://github.com/westenberg/python-meppel-afvalkalender
Author: Westenberg
License: MIT license
Keywords: meppel afvalkalender,afvalkalender,api,async,client
Platform: UNKNOWN
Classifier: Development Status :: 4 - Beta
Classifier: Framework :: AsyncIO
Classifier: Intended Audience :: Developers
Classifier: License :: OSI Approved :: MIT License
Classifier: Natural Language :: English
Classifier: Programming Language :: Python :: 3.7
Classifier: Programming Language :: Python :: 3.8
Classifier: Programming Language :: Python :: 3
Classifier: Topic :: Software Development :: Libraries :: Python Modules
Requires-Dist: aiohttp (>=3.0.0)
Requires-Dist: yarl
